lucqa_tools/__init__.py
lucqa_tools/__main__.py
lucqa_tools/config.py
lucqa_tools/main.py
lucqa_tools/assets/img/logo.png
lucqa_tools/converters/__init__.py
lucqa_tools/converters/base64_pdf.py
lucqa_tools/converters/img_base64.py
lucqa_tools/kubernetes/__init__.py
lucqa_tools/kubernetes/k8s_logic.py
lucqa_tools/kubernetes/k8s_viewer.py
lucqa_tools/ui/__init__.py
lucqa_tools/ui/base64_converter.py
lucqa_tools/ui/components.py
lucqa_tools-1.1.1.dist-info/METADATA
lucqa_tools-1.1.1.dist-info/WHEEL
lucqa_tools-1.1.1.dist-info/entry_points.txt
lucqa_tools-1.1.1.dist-info/top_level.txt
lucqa_tools-1.1.1.dist-info/RECORD
